Workbook

Sheet Inputs
A1: Renewable energy case study
A2: Parameter | B2: Value | C2: Unit | D2: Formula / Note
A3: Project Capacity | B3: 50 | C3: MW | D3: Input
A4: Total CapEx | B4: 40000000 | C4: € | D4: Input
A5: Debt Percentage | B5: 0.7 | C5: % | D5: Input
A6: Equity Percentage | B6: 0.3 | C6: % | D6: Input
A7: Debt Interest Rate | B7: 0.05 | C7: % | D7: Input
A8: Debt Tenor | B8: 12 | C8: years | D8: Input
A9: Tariff (base case) | B9: 70 | C9: €/MWh | D9: Input (guaranteed 15 yrs)
A10: Energy Yield | B10: 1700 | C10: hours/year | D10: Input
A11: OPEX | B11: 500000 | C11: €/year | D11: Input
A12: Target DSCR | B12: 1.3 | C12: – | D12: Input
A13: Corporate Tax Rate | B13: 0.2 | C13: % | D13: Input
A14: Model Life | B14: 15 | C14: years | D14: Input
A15: Asset Useful Life | B15: 15 | C15: years | D15: Input
A16: Tariff Inflation / Escalation Rate | B16: 0.0% or 0.05% | C16: % | D16: Input
A17: OPEX Inflation / Escalation Rate | B17: 0.0% or 0.02% | C17: % | D17: Input
A18: DSRA Coverage Period | B18: 6 | C18: months | D18: Input
A21: Parameter | B21: Value | C21: Unit | D21: Formula / Source
A22: Annual Hours | B22: 8760 | C22: h/year | D22: Standard annual hours
A23: Annual Generation | B23: 85000 | C23: MWh | D23: Capacity × Energy yield
A24: Annual Revenue | B24: 5950000 | C24: € | D24: Annual generation × Tariff
A25: Debt Amount | B25: 28000000 | C25: € | D25: CapEx × Debt %
A26: Equity Amount | B26: 12000000 | C26: € | D26: CapEx × Equity %
A27: Annual Debt Service (Annuity) | B27: 3159111.5 | C27: € | D27: PMT(interest rate, tenor, debt)
A28: Interest (Year 1) | B28: 1400000 | C28: € | D28: Opening debt × Interest rate
A29: Depreciation Expense | B29: 2666666.7 | C29: €/year | D29: CapEx ÷ Asset life
A30: Taxable Income (Year 1) | B30: 1383333.3 | C30: € | D30: Revenue − OPEX − Interest − Depreciation
A31: Corporate Tax (Year 1) | B31: 276666.67 | C31: € | D31: Taxable income × Tax rate
A32: CFADS (after tax) | B32: 4893333.3 | C32: € | D32: (EBIT × (1−tax)) + Depreciation
A33: Base Case DSCR | B33: 1.54896 | C33: ratio | D33: CFADS ÷ Debt service
... A36: Equity CF (year 0) | B36: -13579556 | C36: € | D36: −(Equity + DSRA funding)

Sheet Debt scheduling
A1: Year | B1: Calendar Year | C1: Opening Debt (€) | D1: Interest (€) | E1: Debt Service (Annuity) (€) | F1: Principal (€) | G1: Closing Debt (€) | H1: CFADS after tax (€) | I1: DSCR after tax
A2: 1 | B2: 2025 | C2: 28000000 | D2: =C2*5% -> 1400000 | E2: =PMT(5%, 12, -28000000) -> 3159111.5 | F2: =E2-D2 -> 1759111.5 | G2: =C2-F2 -> 26240889 | H2: =Inputs!$B$24-Inputs!$B$11-'Debt scheduling'!D2-Depreciation!$C$10 -> 1383333 | I2: =H2/E2 -> 0.43788673
A3: 2 | B3: 2026 | C3: =C2-F2 -> 26240889 | D3: =C3*5% -> 1312044.4 | E3: =PMT(5%, 12, -28000000) -> 3159111.5 | F3: =E3-D3 -> 1847067.1 | G3: =C3-F3 -> 24393821 | H3: =Inputs!$B$24-Inputs!$B$11-'Debt scheduling'!D3-Depreciation!$C$10 -> 1471288.6 | I3: =H3/E3 -> 0.4657286
A4: 3 | B4: 2027 | C4: =C3-F3 -> 24393821 | D4: =C4*5% -> 1219691.1 | E4: =PMT(5%, 12, -28000000) -> 3159111.5 | F4: =E4-D4 -> 1939420.4 | G4: =C4-F4 -> 22454401 | H4: =Inputs!$B$24-Inputs!$B$11-'Debt scheduling'!D4-Depreciation!$C$10 -> 1563641.9 | I4: =H4/E4 -> 0.49496257
A5: 4 | B5: 2028 | C5: =C4-F4 -> 22454401 | D5: =C5*5% -> 1122720.1 | E5: =PMT(5%, 12, -28000000) -> 3159111.5 | F5: =E5-D5 -> 2036391.4 | G5: =C5-F5 -> 20418010 | H5: =Inputs!$B$24-Inputs!$B$11-'Debt scheduling'!D5-Depreciation!$C$10 -> 1660612.9 | I5: =H5/E5 -> 0.52565823
A6: 5 | B6: 2029 | C6: =C5-F5 -> 20418010 | D6: =C6*5% -> 1020900.5 | E6: =PMT(5%, 12, -28000000) -> 3159111.5 | F6: =E6-D6 -> 2138211 | G6: =C6-F6 -> 18279799 | H6: =Inputs!$B$24-Inputs!$B$11-'Debt scheduling'!D6-Depreciation!$C$10 -> 1762432.5 | I6: =H6/E6 -> 0.55788868
A7: 6 | B7: 2030 | C7: =C6-F6 -> 18279799 | D7: =C7*5% -> 913989.93 | E7: =PMT(5%, 12, -28000000) -> 3159111.5 | F7: =E7-D7 -> 2245121.5 | G7: =C7-F7 -> 16034677 | H7: =Inputs!$B$24-Inputs!$B$11-'Debt scheduling'!D7-Depreciation!$C$10 -> 1869343.1 | I7: =H7/E7 -> 0.59173064
A8: 7 | B8: 2031 | C8: =C7-F7 -> 16034677 | D8: =C8*5% -> 801733.85 | E8: =PMT(5%, 12, -28000000) -> 3159111.5 | F8: =E8-D8 -> 2357377.6 | G8: =C8-F8 -> 13677299 | H8: =Inputs!$B$24-Inputs!$B$11-'Debt scheduling'!D8-Depreciation!$C$10 -> 1981599.1 | I8: =H8/E8 -> 0.62726471
A9: 8 | B9: 2032 | C9: =C8-F8 -> 13677299 | D9: =C9*5% -> 683864.97 | E9: =PMT(5%, 12, -28000000) -> 3159111.5 | F9: =E9-D9 -> 2475246.5 | G9: =C9-F9 -> 11202053 | H9: =Inputs!$B$24-Inputs!$B$11-'Debt scheduling'!D9-Depreciation!$C$10 -> 2099468 | I9: =H9/E9 -> 0.66457548
A10: 9 | B10: 2033 | C10: =C9-F9 -> 11202053 | D10: =C10*5% -> 560102.65 | E10: =PMT(5%, 12, -28000000) -> 3159111.5 | F10: =E10-D10 -> 2599008.8 | G10: =C10-F10 -> 8603044.1 | H10: =Inputs!$B$24-Inputs!$B$11-'Debt scheduling'!D10-Depreciation!$C$10 -> 2223230.4 | I10: =H10/E10 -> 0.70375179
A11: 10 | B11: 2034 | C11: =C10-F10 -> 8603044.1 | D11: =C11*5% -> 430152.21 | E11: =PMT(5%, 12, -28000000) -> 3159111.5 | F11: =E11-D11 -> 2728959.3 | G11: =C11-F11 -> 5874084.8 | H11: =Inputs!$B$24-Inputs!$B$11-'Debt scheduling'!D11-Depreciation!$C$10 -> 2353180.8 | I11: =H11/E11 -> 0.74488691
A12: 11 | B12: 2035 | C12: =C11-F11 -> 5874084.8 | D12: =C12*5% -> 293704.24 | E12: =PMT(5%, 12, -28000000) -> 3159111.5 | F12: =E12-D12 -> 2865407.2 | G12: =C12-F12 -> 3008677.6 | H12: =Inputs!$B$24-Inputs!$B$11-'Debt scheduling'!D12-Depreciation!$C$10 -> 2489628.8 | I12: =H12/E12 -> 0.78807879
A13: 12 | B13: 2036 | C13: =C12-F12 -> 3008677.6 | D13: =C13*5% -> 150433.88 | E13: =PMT(5%, 12, -28000000) -> 3159111.5 | F13: =E13-D13 -> 3008677.6 | G13: =C13-F13 -> -4.1909516e-09 | H13: =Inputs!$B$24-Inputs!$B$11-'Debt scheduling'!D13-Depreciation!$C$10 -> 2632899.1 | I13: =H13/E13 -> 0.83343027

Sheet Cashflows
A1: Year | B1: Revenue (€) | C1: OPEX (€) | D1: Interest (€) | E1: Tax (€) | F1: CFADS before tax (€) | G1: Depreciation | H1: CFADS after tax (€) | I1: Debt Service (€) | J1: DSCR after tax | K1: Equity CF (€) | L1: Cum. Equity CF
A2: 1 | B2: 5950000 | C2: 500000 | D2: ='Debt scheduling'!D2 -> 1400000 | E2: =(Inputs!$B$24-Inputs!$B$11-Cashflows!D2-Cashflows!G2)*20% -> 276666.67 | F2: =B2-C2 -> 5450000 | G2: =Inputs!$B$4/Inputs!$B$15 -> 2666666.7 | H2: =F2-E2 -> 5173333.3 | I2: =-PMT(Inputs!$B$7,Inputs!$B$8,Inputs!$B$25) -> 3159111.5 | J2: =H2/I2 -> 1.6375913 | K2: =H2-I2 -> 2014221.9 | L2: -13579556
A3: 2 | B3: 5950000 | C3: 500000 | D3: ='Debt scheduling'!D3 -> 1312044.4 | E3: =(Inputs!$B$24-Inputs!$B$11-Cashflows!D3-Cashflows!G3)*20% -> 294257.78 | F3: =B3-C3 -> 5450000 | G3: =Inputs!$B$4/Inputs!$B$15 -> 2666666.7 | H3: =F3-E3 -> 5155742.2 | I3: =-PMT(Inputs!$B$7,Inputs!$B$8,Inputs!$B$25) -> 3159111.5 | J3: =H3/I3 -> 1.6320229 | K3: =H3-I3 -> 1996630.7 | L3: =L2+K2 -> -11565334
A4: 3 | B4: 5950000 | C4: 500000 | D4: ='Debt scheduling'!D4 -> 1219691.1 | E4: =(Inputs!$B$24-Inputs!$B$11-Cashflows!D4-Cashflows!G4)*20% -> 312728.45 | F4: =B4-C4 -> 5450000 | G4: =Inputs!$B$4/Inputs!$B$15 -> 2666666.7 | H4: =F4-E4 -> 5137271.5 | I4: =-PMT(Inputs!$B$7,Inputs!$B$8,Inputs!$B$25) -> 3159111.5 | J4: =H4/I4 -> 1.6261761 | K4: =H4-I4 -> 1978160.1 | L4: =L3+K3 -> -9568703.4
A5: 4 | B5: 5950000 | C5: 500000 | D5: ='Debt scheduling'!D5 -> 1122720.1 | E5: =(Inputs!$B$24-Inputs!$B$11-Cashflows!D5-Cashflows!G5)*20% -> 332122.66 | F5: =B5-C5 -> 5450000 | G5: =Inputs!$B$4/Inputs!$B$15 -> 2666666.7 | H5: =F5-E5 -> 5117877.3 | I5: =-PMT(Inputs!$B$7,Inputs!$B$8,Inputs!$B$25) -> 3159111.5 | J5: =H5/I5 -> 1.620037 | K5: =H5-I5 -> 1958765.9 | L5: =L4+K4 -> -7590543.3
A6: 5 | B6: 5950000 | C6: 500000 | D6: ='Debt scheduling'!D6 -> 1020900.5 | E6: =(Inputs!$B$24-Inputs!$B$11-Cashflows!D6-Cashflows!G6)*20% -> 352486.57 | F6: =B6-C6 -> 5450000 | G6: =Inputs!$B$4/Inputs!$B$15 -> 2666666.7 | H6: =F6-E6 -> 5097513.4 | I6: =-PMT(Inputs!$B$7,Inputs!$B$8,Inputs!$B$25) -> 3159111.5 | J6: =H6/I6 -> 1.6135909 | K6: =H6-I6 -> 1938401.9 | L6: =L5+K5 -> -5631777.5
A7: 6 | B7: 5950000 | C7: 500000 | D7: ='Debt scheduling'!D7 -> 913989.93 | E7: =(Inputs!$B$24-Inputs!$B$11-Cashflows!D7-Cashflows!G7)*20% -> 373868.68 | F7: =B7-C7 -> 5450000 | G7: =Inputs!$B$4/Inputs!$B$15 -> 2666666.7 | H7: =F7-E7 -> 5076131.3 | I7: =-PMT(Inputs!$B$7,Inputs!$B$8,Inputs!$B$25) -> 3159111.5 | J7: =H7/I7 -> 1.6068225 | K7: =H7-I7 -> 1917019.8 | L7: =L6+K6 -> -3693375.5
A8: 7 | B8: 5950000 | C8: 500000 | D8: ='Debt scheduling'!D8 -> 801733.85 | E8: =(Inputs!$B$24-Inputs!$B$11-Cashflows!D8-Cashflows!G8)*20% -> 396319.9 | F8: =B8-C8 -> 5450000 | G8: =Inputs!$B$4/Inputs!$B$15 -> 2666666.7 | H8: =F8-E8 -> 5053680.1 | I8: =-PMT(Inputs!$B$7,Inputs!$B$8,Inputs!$B$25) -> 3159111.5 | J8: =H8/I8 -> 1.5997157 | K8: =H8-I8 -> 1894568.6 | L8: =L7+K7 -> -1776355.7
A9: 8 | B9: 5950000 | C9: 500000 | D9: ='Debt scheduling'!D9 -> 683864.97 | E9: =(Inputs!$B$24-Inputs!$B$11-Cashflows!D9-Cashflows!G9)*20% -> 419893.67 | F9: =B9-C9 -> 5450000 | G9: =Inputs!$B$4/Inputs!$B$15 -> 2666666.7 | H9: =F9-E9 -> 5030106.3 | I9: =-PMT(Inputs!$B$7,Inputs!$B$8,Inputs!$B$25) -> 3159111.5 | J9: =H9/I9 -> 1.5922535 | K9: =H9-I9 -> 1870994.8 | L9: =L8+K8 -> 118212.93
A10: 9 | B10: 5950000 | C10: 500000 | D10: ='Debt scheduling'!D10 -> 560102.65 | E10: =(Inputs!$B$24-Inputs!$B$11-Cashflows!D10-Cashflows!G10)*20% -> 444646.14 | F10: =B10-C10 -> 5450000 | G10: =Inputs!$B$4/Inputs!$B$15 -> 2666666.7 | H10: =F10-E10 -> 5005353.9 | I10: =-PMT(Inputs!$B$7,Inputs!$B$8,Inputs!$B$25) -> 3159111.5 | J10: =H10/I10 -> 1.5844182 | K10: =H10-I10 -> 1846242.4 | L10: =L9+K9 -> 1989207.8
A11: 10 | B11: 5950000 | C11: 500000 | D11: ='Debt scheduling'!D11 -> 430152.21 | E11: =(Inputs!$B$24-Inputs!$B$11-Cashflows!D11-Cashflows!G11)*20% -> 470636.23 | F11: =B11-C11 -> 5450000 | G11: =Inputs!$B$4/Inputs!$B$15 -> 2666666.7 | H11: =F11-E11 -> 4979363.8 | I11: =-PMT(Inputs!$B$7,Inputs!$B$8,Inputs!$B$25) -> 3159111.5 | J11: =H11/I11 -> 1.5761912 | K11: =H11-I11 -> 1820252.3 | L11: =L10+K10 -> 3835450.2
A12: 11 | B12: 5950000 | C12: 500000 | D12: ='Debt scheduling'!D12 -> 293704.24 | E12: =(Inputs!$B$24-Inputs!$B$11-Cashflows!D12-Cashflows!G12)*20% -> 497925.82 | F12: =B12-C12 -> 5450000 | G12: =Inputs!$B$4/Inputs!$B$15 -> 2666666.7 | H12: =F12-E12 -> 4952074.2 | I12: =-PMT(Inputs!$B$7,Inputs!$B$8,Inputs!$B$25) -> 3159111.5 | J12: =H12/I12 -> 1.5675528 | K12: =H12-I12 -> 1792962.7 | L12: =L11+K11 -> 5655702.5
A13: 12 | B13: 5950000 | C13: 500000 | D13: ='Debt scheduling'!D13 -> 150433.88 | E13: =(Inputs!$B$24-Inputs!$B$11-Cashflows!D13-Cashflows!G13)*20% -> 526579.89 | F13: =B13-C13 -> 5450000 | G13: =Inputs!$B$4/Inputs!$B$15 -> 2666666.7 | H13: =F13-E13 -> 4923420.1 | I13: =-PMT(Inputs!$B$7,Inputs!$B$8,Inputs!$B$25) -> 3159111.5 | J13: =H13/I13 -> 1.5584825 | K13: =H13-I13 -> 1764308.6 | L13: =L12+K12 -> 7448665.2
A14: 13 | B14: 5950000 | C14: 500000 | D14: ='Debt scheduling'!D14 -> 0 | E14: =(Inputs!$B$24-Inputs!$B$11-Cashflows!D14-Cashflows!G14)*20% -> 556666.67 | F14: =B14-C14 -> 5450000 | G14: =Inputs!$B$4/Inputs!$B$15 -> 2666666.7 | H14: =F14-E14 -> 4893333.3 | I14: =-PMT(Inputs!$B$7,Inputs!$B$8,Inputs!$B$25) -> 3159111.5 | J14: =H14/I14 -> 1.5489587 | K14: =H14-I14 -> 1734221.9 | L14: =L13+K13 -> 9212973.8
... A16: 15 | B16: 5950000 | C16: 500000 | D16: ='Debt scheduling'!D16 -> 0 | E16: =(Inputs!$B$24-Inputs!$B$11-Cashflows!D16-Cashflows!G16)*20% -> 556666.67 | F16: =B16-C16 -> 5450000 | G16: =Inputs!$B$4/Inputs!$B$15 -> 2666666.7 | H16: =F16-E16 -> 4893333.3 | I16: =-PMT(Inputs!$B$7,Inputs!$B$8,Inputs!$B$25) -> 3159111.5 | J16: =H16/I16 -> 1.5489587 | K16: =H16-I16 -> 1734221.9 | L16: =L15+K15 -> 12681417

Sheet IRR
B2: Year | C2: CFADS after tax (€) | D2: Equity CF (€)
B3: 0 | C3: -40000000 | D3: -13579556
B4: 1 | C4: =Cashflows!H2 -> 5173333.3 | D4: =Cashflows!K2 -> 2014221.9
B5: 2 | C5: =Cashflows!H3 -> 5155742.2 | D5: =Cashflows!K3 -> 1996630.7
B6: 3 | C6: =Cashflows!H4 -> 5137271.5 | D6: =Cashflows!K4 -> 1978160.1
B7: 4 | C7: =Cashflows!H5 -> 5117877.3 | D7: =Cashflows!K5 -> 1958765.9
B8: 5 | C8: =Cashflows!H6 -> 5097513.4 | D8: =Cashflows!K6 -> 1938401.9
B9: 6 | C9: =Cashflows!H7 -> 5076131.3 | D9: =Cashflows!K7 -> 1917019.8
B10: 7 | C10: =Cashflows!H8 -> 5053680.1 | D10: =Cashflows!K8 -> 1894568.6
B11: 8 | C11: =Cashflows!H9 -> 5030106.3 | D11: =Cashflows!K9 -> 1870994.8
B12: 9 | C12: =Cashflows!H10 -> 5005353.9 | D12: =Cashflows!K10 -> 1846242.4
B13: 10 | C13: =Cashflows!H11 -> 4979363.8 | D13: =Cashflows!K11 -> 1820252.3
B14: 11 | C14: =Cashflows!H12 -> 4952074.2 | D14: =Cashflows!K12 -> 1792962.7
B15: 12 | C15: =Cashflows!H13 -> 4923420.1 | D15: 3434865
B16: 13 | C16: =Cashflows!H14 -> 4893333.3 | D16: 4893333
B17: 14 | C17: =Cashflows!H15 -> 4893333.3 | D17: 4893333
B18: 15 | C18: =Cashflows!H16 -> 4893333.3 | D18: 4893333
B20: Metric | D20: Value
B21: Project IRR (Unlevered) | D21: ≈ 9.34%
B22: Equity IRR (Leveraged) | D22: ≈ 14.08%

Sheet Depreciation
A1: Assumptions
A2: Item | C2: Value | D2: Description
A3: Total CAPEX | C3: 40000000 | D3: Total project investment cost
A4: Asset Useful Life | C4: 15 years | D4: Same as project model period
A5: Depreciation Method | C5: Straight-Line | D5: Equal amount each year
A6: Residual Value | C6: 0 | D6: No residual (salvage) value assumed
A8: Year | B8: Opening Book Value (€) | C8: Depreciation Expense (€) | D8: Closing Book Value (€)
A9: 0 | B9: 40000000 | C9: – | D9: 40000000
A10: 1 | B10: 40000000 | C10: 2666667 | D10: 37333333
A11: 2 | B11: 37333333 | C11: 2666667 | D11: 34666667
A12: 3 | B12: 34666667 | C12: 2666667 | D12: 32000000
A13: 4 | B13: 32000000 | C13: 2666667 | D13: 29333333
A14: 5 | B14: 29333333 | C14: 2666667 | D14: 26666667
A15: 6 | B15: 26666667 | C15: 2666667 | D15: 24000000
A16: 7 | B16: 24000000 | C16: 2666667 | D16: 21333333
A17: 8 | B17: 21333333 | C17: 2666667 | D17: 18666667
A18: 9 | B18: 18666667 | C18: 2666667 | D18: 16000000
A19: 10 | B19: 16000000 | C19: 2666667 | D19: 13333333
A20: 11 | B20: 13333333 | C20: 2666667 | D20: 10666667
A21: 12 | B21: 10666667 | C21: 2666667 | D21: 8000000
... A24: 15 | B24: 2666667 | C24: 2666667 | D24: 0

Sheet DSRA
A1: Item | C1: Value | E1: Description
A2: Annual Debt Service | C2: ='Debt scheduling'!E2 -> 3159111.5 | E2: Fixed annuity payment each year
A3: DSRA Coverage | C3: 6 months (0.5 × annual debt service) | E3: Typical lender requirement
A4: Initial Funding Year | C4: Year 0 (Financial Close) | E4: Funded before operations
A5: Release Year | C5: Year 12 (Final Loan Year) | E5: Released after full debt repayment
A6: Reserve Target | C6: 1579556 | E6: Half of one year’s debt service
B8: Year | C8: Opening Balance (€) | D8: DSRA Funding (+) | E8: DSRA Release (−) | F8: Closing Balance (€)
B9: 0 | C9: 0 | D9: 1579556 | E9: 0 | F9: ='Debt scheduling'!E2*0.5 -> 1579555.7
B10: 1 | C10: =F9 -> 1579555.7 | D10: 0 | E10: 0 | F10: ='Debt scheduling'!E3*0.5 -> 1579555.7
B11: 2 | C11: =F10 -> 1579555.7 | D11: 0 | E11: 0 | F11: ='Debt scheduling'!E4*0.5 -> 1579555.7
B12: 3 | C12: =F11 -> 1579555.7 | D12: 0 | E12: 0 | F12: ='Debt scheduling'!E5*0.5 -> 1579555.7
B13: 4 | C13: =F12 -> 1579555.7 | D13: 0 | E13: 0 | F13: ='Debt scheduling'!E6*0.5 -> 1579555.7
B14: 5 | C14: =F13 -> 1579555.7 | D14: 0 | E14: 0 | F14: ='Debt scheduling'!E7*0.5 -> 1579555.7
B15: 6 | C15: =F14 -> 1579555.7 | D15: 0 | E15: 0 | F15: ='Debt scheduling'!E8*0.5 -> 1579555.7
B16: 7 | C16: =F15 -> 1579555.7 | D16: 0 | E16: 0 | F16: ='Debt scheduling'!E9*0.5 -> 1579555.7
B17: 8 | C17: =F16 -> 1579555.7 | D17: 0 | E17: 0 | F17: ='Debt scheduling'!E10*0.5 -> 1579555.7
B18: 9 | C18: =F17 -> 1579555.7 | D18: 0 | E18: 0 | F18: ='Debt scheduling'!E11*0.5 -> 1579555.7
B19: 10 | C19: =F18 -> 1579555.7 | D19: 0 | E19: 0 | F19: ='Debt scheduling'!E12*0.5 -> 1579555.7
B20: 11 | C20: =F19 -> 1579555.7 | D20: 0 | E20: 0 | F20: ='Debt scheduling'!E13*0.5 -> 1579555.7
B21: 12 | C21: =F20 -> 1579555.7 | D21: 0 | E21: −1,579,556 | F21: ='Debt scheduling'!E14*0.5 -> 0

Sheet Summary
A2: Metric | B2: Value
A3: CapEx (€) | B3: 40000000
A4: Debt (€) | B4: 28000000
A5: Equity (€) | B5: 12000000
A6: Tariff | B6: 70 MWh/€
A7: Annual Generation (kWh) | B7: 85000000
A8: Revenue (€) | B8: 5950000
A9: Annual Debt Service (€) | B9: 3159111
A10: CFADS after tax (€) | B10: =Cashflows!H2 -> 5173333.3
A11: Base Case DSCR (after tax) | B11: 1.549
A12: Minimum DSCR (after tax) | B12: 1.549
A13: Tariff Needed for Target DSCR =1.3 | B13: 58.64 MWh/€
A14: Equity IRR | B14: ≈ 14.08%

Sheet Dashbaord
B2: 50 MW Solar PV Project – Financial Summary Dashboard
B6: Project Capacity | E6: Investment Structure | H6: Tariff & OPEX | K6: Tax & Loan Terms | N6: Sensitivity
B8: Capacity: 50 MW | E8: Capacity: 50 MW | H8: Tariff: €70/MWh | K8: Tax Rate: 20%
E9: Debt: €28,000,000 (70%) | K9: Loan Tenor: 12 years
B10: Energy Yield: 85,000 MWh/year | E10: Equity: €12,000,000 (30%) | H10: OPEX: €500,000/year | K10: Interest Rate: 5%
K11: Annual Debt Service: €3,159,111
B13: Project IRR (Unlevered) | E13: Equity IRR (Leveraged) | H13: Base Case DSCR | K13: Required Tariff for DSCR 1.30
B15: 9.34% | E15: 0.1408 | H15: 1.5695 | K15: 58.64 €/MWh
